dldtrainer/__init__.py
dldtrainer/callbacks/__init__.py
dldtrainer/callbacks/callbacks.py
dldtrainer/callbacks/log_history.py
dldtrainer/callbacks/losses_recorder.py
dldtrainer/callbacks/model_checkpoint.py
dldtrainer/callbacks/multi_losses_recorder.py
dldtrainer/criterion/__init__.py
dldtrainer/criterion/criterion.py
dldtrainer/engine/__init__.py
dldtrainer/engine/base.py
dldtrainer/engine/comm.py
dldtrainer/engine/engine.py
dldtrainer/engine/launch.py
dldtrainer/engine/trainer.py
dldtrainer/metric/__init__.py
dldtrainer/metric/accuracy_recorder.py
dldtrainer/metric/eval_tools/__init__.py
dldtrainer/metric/eval_tools/acc.py
dldtrainer/metric/eval_tools/classification_report.py
dldtrainer/metric/eval_tools/eval_utils.py
dldtrainer/metric/eval_tools/evaluate.py
dldtrainer/metric/eval_tools/iou.py
dldtrainer/metric/eval_tools/metrics.py
dldtrainer/metric/eval_tools/pandas_tools.py
dldtrainer/metric/eval_tools/pr.py
dldtrainer/metric/eval_tools/psnr.py
dldtrainer/metric/eval_tools/roc.py
dldtrainer/metric/eval_tools/verification.py
dldtrainer/optimizer/__init__.py
dldtrainer/optimizer/build_optimizer.py
dldtrainer/pruning/__init__.py
dldtrainer/pruning/nni_pruning.py
dldtrainer/pruning/slim_pruning.py
dldtrainer/pruning/torch_pruning.py
dldtrainer/scheduler/CosineAnnealingLR.py
dldtrainer/scheduler/ExponentialLR.py
dldtrainer/scheduler/MultiStepLR.py
dldtrainer/scheduler/MultiStepValue.py
dldtrainer/scheduler/PolyExpLR.py
dldtrainer/scheduler/WarmUpLR.py
dldtrainer/scheduler/__init__.py
dldtrainer/scheduler/build_scheduler.py
dldtrainer/utils/__init__.py
dldtrainer/utils/file_utils.py
dldtrainer/utils/image_utils.py
dldtrainer/utils/log.py
dldtrainer/utils/plot_utils.py
dldtrainer/utils/setup_config.py
dldtrainer/utils/summary.py
dldtrainer/utils/torch_data.py
dldtrainer/utils/torch_tools.py
dldtrainer-0.6.0.dist-info/LICENCE
dldtrainer-0.6.0.dist-info/METADATA
dldtrainer-0.6.0.dist-info/WHEEL
dldtrainer-0.6.0.dist-info/top_level.txt
dldtrainer-0.6.0.dist-info/RECORD
