Metadata-Version: 2.1
Name: dldtrainer
Version: 0.6.0
Summary: dldtrainer
Home-page: https://github.com/PanJinquan
Author: PanJinquan
Author-email: pan_jinquan@163.com
License: MIT
Platform: UNKNOWN
License-File: LICENCE
